README.rst
setup.py
docs/HISTORY.txt
docs/INSTALL.txt
docs/LICENSE.GPL
docs/LICENSE.txt
docs/TODO.txt
jarn/__init__.py
jarn.jsi18n.egg-info/PKG-INFO
jarn.jsi18n.egg-info/SOURCES.txt
jarn.jsi18n.egg-info/dependency_links.txt
jarn.jsi18n.egg-info/entry_points.txt
jarn.jsi18n.egg-info/namespace_packages.txt
jarn.jsi18n.egg-info/not-zip-safe
jarn.jsi18n.egg-info/requires.txt
jarn.jsi18n.egg-info/top_level.txt
jarn/jsi18n/__init__.py
jarn/jsi18n/configure.zcml
jarn/jsi18n/jsi18n.js
jarn/jsi18n/view.py
jarn/jsi18n/profiles/default/jsregistry.xml
jarn/jsi18n/profiles/default/metadata.xml
jarn/jsi18n/tests/jarn.i18n.spec.js
jarn/jsi18n/tests/testRunner.html
jarn/jsi18n/tests/jasmine/MIT.LICENSE
jarn/jsi18n/tests/jasmine/jasmine-html.js
jarn/jsi18n/tests/jasmine/jasmine.css
jarn/jsi18n/tests/jasmine/jasmine.js
jarn/jsi18n/tests/jasmine/jasmine_favicon.png