Metadata-Version: 1.0
Name: jarn.jsi18n
Version: 0.2
Summary: Plone i18n for JavaScript
Home-page: https://github.com/ggozad/jarn.jsi18n
Author: Yiorgis Gozadinos
Author-email: ggozad@jarn.com
License: GPL
Keywords: plone javascript i18n
Platform: UNKNOWN
Classifier: Development Status :: 5 - Production/Stable
Classifier: Framework :: Plone
Classifier: Intended Audience :: Developers
Classifier: Programming Language :: Python
Classifier: Programming Language :: JavaScript
